{
  "title": "15Five",
  "product_url": "http://15five.com/",
  "description": "15Five is the leading employee communication platform for managers to gain insights into employee progress, and for employees to receive the feedback they need to succeed.\n\nThis brief, automated weekly process leads to meaningful conversations about everything from how to improve an employee\u2019s role, to the creation of brilliant product innovations.",
  "producthunt_url": "https://www.producthunt.com/products/15five",
  "crawl_timestamp": "2025-04-02T08:07:10.040485"
}