{
  "title": "App in the Air",
  "product_url": "https://www.appintheair.mobi/",
  "description": "Editors Choice \u25c6\u25c6 Best of 2018 Watch app \u25c6\u25c6 Featured in Forbes, Wired, CBS News, Travel+Leisure and more.\n\nApp in the Air is the single place to track your itineraries, boarding passes and manage your miles across airlines. Avoid hours of searching for the best times, price or airline with our sophisticated AI booking system that understands your flying needs and loyalties.",
  "producthunt_url": "https://www.producthunt.com/products/app-in-the-air",
  "crawl_timestamp": "2025-04-02T07:45:39.157245"
}