{
  "title": "Beezy",
  "product_url": "https://www.beezy.net/",
  "description": "Beezy is the modern intranet that\u2019s part of the Appspace workplace experience platform. Appspace provides the solutions you need to unify your physical and digital workplace. Digital signage and kiosks, space reservation, and more \u2013 only Appspace brings it all together in one simple platform.",
  "producthunt_url": "https://www.producthunt.com/products/beezy",
  "crawl_timestamp": "2025-03-31T23:54:55.813301"
}