{
  "title": "Boost Sales with Smart Demand Generation",
  "product_url": "https://slixta.com/demand-generation",
  "description": "Slixta is your go-to platform for smarter demand generation. Capture leads, build landing pages, and automate drip campaigns\u2014all in one place. Turn prospects into buyers with tool that streamline your sales funnel, optimize conversions, and boost revenue.",
  "producthunt_url": "https://www.producthunt.com/products/boost-sales-with-smart-demand-generation",
  "crawl_timestamp": "2025-04-04T05:12:49.131034"
}