{
  "title": "Chaos & Cyber Culture",
  "product_url": "https://books.google.com/books",
  "description": "Chaos and CyberCulture brings together his provocative, futuristic writings, lively interviews and cogent conversations with a variety of writers and thinkers. Chaos and CyberCulture defines the emergence of the New Breed of the Information Age, who are creating the cyberdelic politics and culture of the 21st Century.",
  "producthunt_url": "https://www.producthunt.com/products/tourism-travel-and-blogging",
  "crawl_timestamp": "2025-04-02T03:40:44.219626"
}