{
  "title": "Chestly",
  "product_url": "https://apps.apple.com/ph/app/chestly-organize-your-items/id6670334914",
  "description": "\"Stop asking 'Honey, where's my...?' Chestly remembers so you don't have to! Easily catalog and find your stuff with this smart organizer app. With Siri integration, your items are just a question away. Perfect for forgetful folks and busy households.\"",
  "producthunt_url": "https://www.producthunt.com/products/chestly",
  "crawl_timestamp": "2025-04-04T14:04:00.191210"
}