{
  "title": "Choice Touch",
  "product_url": "https://choicetechlab.com/products/employee-management-system",
  "description": "Elevate sales strategy with our advanced field force automation. Seamlessly streamline operations, automate workflows, & monitor real-time activities. Empower your sales team to maximize productivity & close more deals, while our app takes care of the details.",
  "producthunt_url": "https://www.producthunt.com/products/choice-touch",
  "crawl_timestamp": "2025-04-04T05:13:23.894937"
}