{
  "title": "dartShell",
  "product_url": "https://github.com/hsduren/dartshell/tree/main",
  "description": "MacOS SSH/SFTP client with: \u2022 Quick Connection: Stores IPs/keys \u2022 Batch Connection: Multiple servers \u2022 Auto-Suggestions, history \u2022 Built-in SFTP \u2022 Real-time stats \u2022 Split screen \u2022 Buffer search \u2022 Group commands \u2022 Export/Import server list",
  "producthunt_url": "https://www.producthunt.com/products/dartshell",
  "crawl_timestamp": "2025-04-03T23:11:13.116165"
}