{
  "title": "Dim Visual Media",
  "product_url": "https://chrome.google.com/webstore/detail/dim-visual-media/fekajhhpndhdfgeffgllhfaddnkjmjbo",
  "description": "Watch your favourite Twitch Stream, YouTube, Google and other visual media content dimmed. Applies dim to every site you have up or visits Dims Streams, Video and Images \u2605 For your study or work session \u2605 For you to watch your favourite content creator",
  "producthunt_url": "https://www.producthunt.com/products/dim-visual-media",
  "crawl_timestamp": "2025-04-02T20:47:05.616313"
}