{
  "title": "Easy Time Clock",
  "product_url": "https://easytimeclock.com/",
  "description": "It's as Easy as 1-2-3!\n\t\n\t\t\t\tStep 1\n\t\tEMPLOYEES CLOCK IN\n\t\t\twith a computer, mobile device, or reader.\t\t\n\t\t\t\tStep 2\n\t\tGENERATE REPORTS\n\t\t\tto view totals, make edits, and digitally approve for payroll.\t\t\n\t\t\t\tStep 3\n\t\tEXPORT PAYROLL\n\t\t\tand relax - you're done. Congratulations! You did it.\t\t\n\n\t\tFabulou",
  "producthunt_url": "https://www.producthunt.com/products/easy-time-clock",
  "crawl_timestamp": "2025-03-31T18:59:35.237258"
}