{
  "title": "EPAY Systems",
  "product_url": "https://www.epaysystems.com/",
  "description": "EPAY is the only complete HR and Payroll software solution designed for employers with a distributed, hourly workforce. EPAY helps lower labor costs and optimize their people\u2014thanks to powerful analytics and unique time and attendance tools\u2014while lightening their HR workload via the easyrobust, end-to-end HR software.",
  "producthunt_url": "https://www.producthunt.com/products/epay-systems",
  "crawl_timestamp": "2025-04-01T01:21:37.317434"
}