{
  "title": "Exist Experience - You Belong",
  "product_url": "https://www.existexperience.com/",
  "description": "Exist is a supportive space where you connect, share, and grow together. With innovative journaling, immersive audio content, and community-driven support, Exist helps you navigate challenges like stress, anxiety, and self-love, offering comfort and connection",
  "producthunt_url": "https://www.producthunt.com/products/exist-experience-you-belong",
  "crawl_timestamp": "2025-04-04T10:15:35.601579"
}