{
  "title": "Hidden Object Game : House Mystery",
  "product_url": "https://play.google.com/store/apps/details",
  "description": "Old House Mystery Secrets: Hidden Object Game is a mind-teasing and soul-stirring game for the best players of hidden object games. Whether you want hidden object games, don\u2019t hesitate because Hidden Object Old House Mystery Secrets has everything you need!",
  "producthunt_url": "https://www.producthunt.com/products/hidden-object-game-house-mystery",
  "crawl_timestamp": "2025-04-02T21:08:04.460183"
}