{
  "title": "iRe5 - Make Your iPhone Great Again",
  "product_url": "https://www.kickstarter.com/projects/ire5/ire5-invisible-storage-makes-your-iphone-great-again",
  "description": "iRe5 is the revolutionary iPhone case with built-in memory expansion. With its integrated microSD card slot and USB Type-C port, iRe5 seamlessly combines sleek design with expanded storage capabilities.",
  "producthunt_url": "https://www.producthunt.com/products/ire5-make-your-iphone-great-again",
  "crawl_timestamp": "2025-04-04T00:43:16.899036"
}