{
  "title": "Kickresume",
  "product_url": "https://www.kickresume.com/",
  "description": "What happens when you combine the world\u2019s most powerful AI with the most powerful resume builder? Try Kickresume \u2014 the world\u2019s most powerful AI resume builder that has already helped more than 3,000,000 job seekers get hired at companies like Tesla, Google, SpaceX, and more.\n\nKickresume will guide you through every step of creating a professional resume and cover letter \u2014 and make every single one of those steps a walk in the park (or a piece of cake, depending on which you like better).",
  "producthunt_url": "https://www.producthunt.com/products/kickresume",
  "crawl_timestamp": "2025-04-02T06:01:32.956191"
}