{
  "title": "Loggly",
  "product_url": "https://www.loggly.com/",
  "description": "Loggly combines monitoring, log analysis, and event alerting in one easy to use, yet powerful platform. This SaaS product helps you find errors in your logs without custom queries. You can then fix your code via our GitHub integration. See why over 10k customers, including 1/3 of the fortune 500 use Loggly. Free trial at Loggly.com",
  "producthunt_url": "https://www.producthunt.com/products/loggly",
  "crawl_timestamp": "2025-04-03T10:25:12.290840"
}