{
  "title": "No-BS SaaS Figma Template MAX",
  "product_url": "https://3sidedcoin.gumroad.com/l/no-bs-saas-template-max",
  "description": "The essential SaaS website template: 15 key pages, desktop & mobile layouts. Lean design, fully customizable, optimized for quick launch. Perfect for startups, freelancers & students. Save time, focus on your product. Priced less than two weeks of coffee.",
  "producthunt_url": "https://www.producthunt.com/products/no-bs-saas-figma-template-max",
  "crawl_timestamp": "2025-04-04T05:48:47.242918"
}