{
  "title": "OpenCraft AI",
  "product_url": "https://opencraftai.com/",
  "description": "OpenCraft AI is a versatile platform designed to enhance professional productivity through advanced AI capabilities. It offers critical thinking and problem-solving for complex math challenges, real-time web searches, and insightful document analysis. With features like an AI-powered writing companion, precise coding assistance, and effortless SQL interactions, OpenCraft AI simplifies complex tasks, providing premium AI solutions that are both affordable and effective.",
  "producthunt_url": "https://www.producthunt.com/products/opencraft-ai",
  "crawl_timestamp": "2025-04-04T05:38:52.444205"
}