{
  "title": "Paradigm Electronics Inc.",
  "product_url": "https://www.paradigm.com/",
  "description": "Paradigm is the speaker company on the leading edge of audio innovation. We are dedicated to keeping you and your family and friends connected to the entertainment you enjoy, wired or wireless, inside or outside. We create original, well-crafted products that you\u2019ll be proud to own, use and share with others.",
  "producthunt_url": "https://www.producthunt.com/products/paradigm-electronics-inc",
  "crawl_timestamp": "2025-04-01T02:17:39.914501"
}