{
  "title": "Paradiddle",
  "product_url": "http://paradiddleapp.com/",
  "description": "Paradiddle lets you play drums in VR without the limitations of the real world. Available for the @OculusRift, @htcvive and WMR headsets on Steam Early Access. \nParadiddle lets you explore your percussion skills freely in a flexible and responsive VR environment. Out now on Early Access on Steam, & soon the Oculus Store!",
  "producthunt_url": "https://www.producthunt.com/products/paradiddle",
  "crawl_timestamp": "2025-04-02T07:54:10.154363"
}