{
  "title": "Passion Planner",
  "product_url": "https://www.kickstarter.com/projects/angeliatrinidad/passion-planner-the-one-place-for-all-your-thought",
  "description": "Passion planner is not an ordinary planner, it is a planner that will keep you going and motivated until you accomplish what you are striving for in life. It has a goal setting planner inside to make sure you keep in mind your goals, motivational quotes and challenges, monthly reflections and sketch pages for your doodles.",
  "producthunt_url": "https://www.producthunt.com/products/passion-planner",
  "crawl_timestamp": "2025-04-03T04:59:54.558079"
}