{
  "title": "Percy",
  "product_url": "https://percy.io/",
  "description": "At Percy, we work at the intersection of design, development, and deployment. Our product is the world\u2019s first truly continuous visual testing platform, helping enable product teams to ship software faster and with confidence in every visual change to their application. Percy is used daily by customers like Google, the New York Times, Stitch Fix, Dollar Shave Club, and Ubuntu.",
  "producthunt_url": "https://www.producthunt.com/products/percy",
  "crawl_timestamp": "2025-04-02T18:07:33.276369"
}