{
  "title": "Personality Spectrum",
  "product_url": "https://personalityhq.com/spectrum",
  "description": "Assess Your Personality Spectrum: A cutting-edge psychometric test to measure 6+24 factors of personality Introducing \"Integrity\", the most useful personality factors. The lite report is sent by email after completion of the test (less than 15 minutes).",
  "producthunt_url": "https://www.producthunt.com/products/personality-spectrum",
  "crawl_timestamp": "2025-04-03T20:54:11.040496"
}