{
  "title": "Pixel Thoughts",
  "product_url": "http://www.pixelthoughts.co/",
  "description": "Pixel Thoughts is your meditation web space. If you experience any sort of anxiety, stress or depression, you can type your worries inside the moon and watch them fly away for 60 seconds surrounded by a relaxing music and background. Release the stress and clear your mind for a healthy life.",
  "producthunt_url": "https://www.producthunt.com/products/pixel-thoughts",
  "crawl_timestamp": "2025-04-03T11:54:28.833029"
}