{
  "title": "PlantIdentify - Plant Detector",
  "product_url": "https://apps.apple.com/us/app/plantidentify-plant-detector/id6504149002",
  "description": "\ud83c\udf3f FREE Plant Identifier App \ud83c\udf3f \ud83d\udcf7Use your camera or a picture to quickly identify plants with AI\ud83c\udf3f Features: \u2022 Instant Plant Identification \u2022 Free to Use \u2022 Multi-Language Support \u2022 Save Identification History",
  "producthunt_url": "https://www.producthunt.com/products/plantidentify-plant-detector",
  "crawl_timestamp": "2025-04-03T22:26:25.398371"
}