{
  "title": "Plasso",
  "product_url": "https://plasso.com/",
  "description": "We are a technology driven, ecommerce platfrom working globally to help entrepreneurs start, manage, and grow their business online! Our purpose is simple, we work with business owners and consumers to pay for things, get paid for things, buy things, and sell things. We make payments simple \ud83e\udd19",
  "producthunt_url": "https://www.producthunt.com/products/plasso",
  "crawl_timestamp": "2025-04-02T06:38:58.409558"
}