{
  "title": "Quokka",
  "product_url": "https://chrome.google.com/webstore/detail/quokka-monitor-webpage-da/agoklhpignkeigeeepfpknnhfmgkfihl",
  "description": "Quokka is a light-weight and easy-to-use chrome extension that helps you to organize all your data of interest in one place. Within one click, you can quickly watch through all the data. The data will be updated with the frequency you given.",
  "producthunt_url": "https://www.producthunt.com/products/quokka-4",
  "crawl_timestamp": "2025-04-02T20:23:25.742406"
}