{
  "title": "Safari Full width for StackOverflow",
  "product_url": "https://apps.apple.com/us/app/full-width-for-so/id6474455354",
  "description": "No more horizontal scrolls on StackOverflow.com! Extension to make StackOverflow page wider The extension is designed to enhance your StackOverflow browsing experience. Say goodbye to annoying horizontal scrolls and limited code snippet views!",
  "producthunt_url": "https://www.producthunt.com/products/safari-full-width-for-stackoverflow",
  "crawl_timestamp": "2025-04-04T00:21:32.168125"
}