{
  "title": "Sitelet.co \u2014 The better link in bio",
  "product_url": "https://sitelet.co/nick",
  "description": "Create a stunning website in just 10 seconds with Sitelet. Choose from two captivating 3D templates, customize your color scheme, and add up to five links. Unlike LinkTree, Sitelet gives you a real website that stands out\u2014not a boring list of links!",
  "producthunt_url": "https://www.producthunt.com/products/sitelet-co-the-better-link-in-bio",
  "crawl_timestamp": "2025-04-04T12:45:35.007495"
}