{
  "title": "Snatch",
  "product_url": "https://snatch.kasper.io/",
  "description": "Beautiful clipboard manager for Windows. Keep your history under control. Snatch will keep every copied element until you decide to clean the history. ou can pin any entry. Pinned entries will stay in place when list is cleared. No matter how long history you have, you can search it in just a fraction o second.",
  "producthunt_url": "https://www.producthunt.com/products/snatch",
  "crawl_timestamp": "2025-04-02T04:46:24.931329"
}