{
  "title": "Stereo for Mac (remastered)",
  "product_url": "https://aquariuscomputer.co/stereo",
  "description": "New Kind of Music Player Now Available. For free trial, or a high value buy only if you want/need it. Stereo is a new, revolutionary interface for a music player, for people who love music. It\u2019s addicting. Stereo works with your Apple Music library.",
  "producthunt_url": "https://www.producthunt.com/products/stereo-for-mac-remastered",
  "crawl_timestamp": "2025-04-04T02:24:43.067068"
}