{
  "title": "SynthLife - Ai Influencer Generator",
  "product_url": "https://synthlife.co/",
  "description": "SynthLife is a platform designed to facilitate the creation, growth, and monetization of virtual influencers. Its an all-in-one solution for individuals or companies looking to dive into the world of virtual influencers, without needing any technical skills.",
  "producthunt_url": "https://www.producthunt.com/products/synthlife-ai-influencer-generator",
  "crawl_timestamp": "2025-04-03T21:54:02.736900"
}