{
  "title": "Team Sports Admin",
  "product_url": "https://enjoy.teamsportsadmin.com/",
  "description": "Thousands of sports organizations of all sizes\u2014from local select programs to MLB\u2122 branded youth organizations\u2014utilize Team Sports Admin's platform and services to accept payments, sign legal documents (via DocuSign\u2122), and manage their organizations online.",
  "producthunt_url": "https://www.producthunt.com/products/team-sports-admin",
  "crawl_timestamp": "2025-04-01T00:54:13.433076"
}