{
  "title": "Thay man hinh Samsung Note 20 Ultra",
  "product_url": "https://thanhtrungmobile.vn/thay-man-hinh-samsung-galaxy-note-20-ultra.html",
  "description": "B\u1ea1n \u0111ang lo l\u1eafng v\u1ec1 chi ph\u00ed thay m\u00e0n h\u00ecnh Samsung Note 20 Ultra? Th\u00e0nh Trung Mobile cam k\u1ebft mang \u0111\u1ebfn gi\u1ea3i ph\u00e1p t\u1ed1i \u01b0u v\u1edbi gi\u00e1 c\u1ea3 h\u1ee3p l\u00fd nh\u1ea5t. Xem chi ti\u1ebft d\u1ecbch v\u1ee5 t\u1ea1i: thanhtrungmobile.vn/thay-man-hinh-samsung-galaxy-note-20-ultra.html",
  "producthunt_url": "https://www.producthunt.com/products/thay-man-hinh-samsung-note-20-ultra-2",
  "crawl_timestamp": "2025-04-04T04:50:38.185398"
}