{
  "title": "ThoughtExchange",
  "product_url": "https://thoughtexchange.com/",
  "description": "ThoughtExchange is for leaders who make big decisions. Get instant, unbiased insights from tens, hundreds, or thousands of people\u2014without spending weeks or months making sense of the data. Engage your organization or community to voice their thoughts and deliver the best solutions to your most pressing challenges. Unify people and make better decisions, faster.",
  "producthunt_url": "https://www.producthunt.com/products/thoughtexchange",
  "crawl_timestamp": "2025-04-01T01:19:05.876791"
}