{
  "title": "TimeOS - Ultimate Task Manager for Pro",
  "product_url": "https://krisxtheory.gumroad.com/l/TimeOS",
  "description": "The most accurate way to report how you spent your time for yourself or your client. Choose the level of detail of the invoice. Set your hourly rate and earn money for productive, high-quality work, right inside the Notion!",
  "producthunt_url": "https://www.producthunt.com/products/timeos-ultimate-task-manager-for-pro",
  "crawl_timestamp": "2025-04-04T11:27:13.612866"
}