{
  "title": "TodayTix",
  "product_url": "http://www.todaytix.com/",
  "description": "TodayTix is your destination for the best-priced theater tickets to Broadway and Off-Broadway shows and performing arts events. As the highest-rated ticketing app in the Play Store, TodayTix is the theater ticket booking app that offers you unparalleled access to your favorite shows at the best prices in town.",
  "producthunt_url": "https://www.producthunt.com/products/todaytix",
  "crawl_timestamp": "2025-04-02T05:04:56.039009"
}