{
  "title": "Tune : AI Car Tuning",
  "product_url": "https://apps.apple.com/us/app/tune-ai-car-tuning/id6523376299",
  "description": "Tune: AI Car Tuning lets you transform your car\u2019s look with just a few clicks. Upload a photo, choose from styles like American muscle, JDM, or off-road, and watch as our AI creates hyper-realistic, cinematic modifications. Revamp your ride today!",
  "producthunt_url": "https://www.producthunt.com/products/tune-ai-car-tuning",
  "crawl_timestamp": "2025-04-04T05:29:11.180741"
}