{
  "title": "Worklis Recruitment",
  "product_url": "https://www.worklis.com/",
  "description": "Worklis is an innovative White Label recruitment software infused with powerful AI capabilities, revolutionizing the hiring process for organizations. By automating the initial screening stage, Worklis significantly reduces manual effort and speeds up the candidate selection process, enabling recruiters to focus their attention on the most promising candidates.",
  "producthunt_url": "https://www.producthunt.com/products/worklis-recruitment",
  "crawl_timestamp": "2025-04-02T20:43:15.940907"
}