{
  "title": "WorkMarketer.io",
  "product_url": "https://join.slack.com/t/workmarketer/shared_invite/enQtNjI0NzQyMTc3NDYwLWQ5NDJlY2ViYzJkMmFjZGE5MDI3NTczOTRlZTcwZjgzZmU2ODk0MTliZTJhZjcwMjI2ZWJkZjU0MGM4OTFiMjY",
  "description": "A slack community created to cater the key areas for a marketer i.e. - Professional growth - Learning from peers around you - Remote opportunities - Exploring different verticals - Gaining knowledge around dealing with uncertain marketing projects",
  "producthunt_url": "https://www.producthunt.com/products/workmarketer-io",
  "crawl_timestamp": "2025-04-03T22:20:13.447704"
}