{
  "title": "Xeams",
  "product_url": "https://www.xeams.com/",
  "description": "Xeams is a secure and powerful mail server for Windows, Linux, Solaris, MacOSX and other flavors of UNIX, and supports SMTP, POP3, and IMAP. Xeams includes a powerful spam filtering engine that eliminates up to 99% of junk email right out of the box. The software offers a flexible approach to email, making it a very user friendly server.",
  "producthunt_url": "https://www.producthunt.com/products/xeams",
  "crawl_timestamp": "2025-04-01T02:35:24.294090"
}