{
  "title": "Xpo Fairs",
  "product_url": "https://www.xpofairs.com/events-box-office/eventdetails/product-hunt-nextech",
  "description": "We're found a way to make trade events faster, easier, cheaper and better for both exhibitors & visitors. Our web-based application hosts fully interactive trade shows in real time with real people. Welcome to the future of international B2B trade \ud83d\udc49\ud83c\udffd use code #ProductHunters for free access",
  "producthunt_url": "https://www.producthunt.com/products/xpo-fairs",
  "crawl_timestamp": "2025-04-04T13:37:04.494141"
}