{
  "title": "YT to MP3 - Free Online Tool",
  "product_url": "https://yttomp3.media/",
  "description": "\ud83d\ude80 Introducing YTToMP3.media\u2014your all-in-one free online tool for converting videos to MP3, WAV, OGG, or OPUS and downloading videos in MP4 format from YouTube, Bilibili, TikTok, Instagram, and more! Compatible with desktop, tablet, and mobile devices, no app installation required. \ud83c\udfa7 Get fast, secure, and high-quality downloads anytime, anywhere. Try it out now and let us know what you think! \ud83d\udd17 #YoutubeToMp3 #YTToMp3  #VideoToMP3 #MP4Downloader #FreeConverter #AudioTools",
  "producthunt_url": "https://www.producthunt.com/products/yt-to-mp3-free-online-tool",
  "crawl_timestamp": "2025-04-04T12:08:45.585839"
}