{
  "title": "Bexi.ai:Free AI Humanizer & AI Detector",
  "product_url": "https://bexi.ai/",
  "description": "BEXI.ai transforms AI-generated content into natural, human-like language, enhancing readability and engagement. Perfect for creators, marketers, freelancers, and businesses, it refines AI text to match your brand voice or personal style.",
  "producthunt_url": "https://www.producthunt.com/products/bexi-ai-free-ai-humanizer-ai-detector",
  "crawl_timestamp": "2025-04-05T00:04:28.067856"
}