{
  "title": "Chat Images",
  "product_url": "https://chatimages.online/",
  "description": "You can edit your images and create images from scratch using our AI system. You can\n- Generate images with your product logo\n- Relight Images,\n- Remove or change image background\n- Add or remove elements to your image while preserving the original image\n- Virtual try ons\n and a lot more just from a simple chat interface.\n\nVisit our site to check out more of what we can offer and the affordable prices.",
  "producthunt_url": "https://www.producthunt.com/products/chat-image",
  "crawl_timestamp": "2025-04-05T03:30:40.506104"
}