{
  "title": "Instant Medium Analytics",
  "product_url": "https://chromewebstore.google.com/detail/instant-medium-analytics/hogkmdhgbpeaoimjbmojggpacjfjcnlo",
  "description": "Discover trending Medium articles, track profiles, and store data offline with MediumStats.com. This Chrome extension offers powerful analytics, content insights, and a user-friendly interface. Save time and enhance your Medium journey with data-driven tools.",
  "producthunt_url": "https://www.producthunt.com/products/instant-medium-analytics",
  "crawl_timestamp": "2025-04-05T04:35:22.743569"
}