{
  "title": "JGDHealth - EMR, IVR, CRM & Mobile Apps",
  "product_url": "https://www.jgdhealth.com/",
  "description": "Transform your healthcare practice with JGDHealth. We\u2019re more than a Healthtech platform. We have the ability to integrate with any existing software providing operational stability and prepare you for future.\nFrom individual practices to publicly listed healthcare institutions, we have transformed a diverse range of clients. \nOur Major Offerings:\n- AI-Powered IVR\n- Integrated EMR\n- Google Review Management\n- Mobile Applications\n- Patient Communications - Email, SMS, WhatsApp\n- Lead Management",
  "producthunt_url": "https://www.producthunt.com/products/emr-ivr-crm-mobile-apps",
  "crawl_timestamp": "2025-04-05T02:42:50.358870"
}