{
  "title": "Maxim AI",
  "product_url": "https://www.getmaxim.ai/",
  "description": "Maxim is an end-to-end AI simulation and evaluation platform (including for the last mile of human-in-the-loop) that empowers modern AI teams to ship their AI agents with quality, reliability, and speed. Its developer stack comprises tools for the full AI lifecycle: experimentation, pre-release testing, and production monitoring & quality checks.\n\nMaxim's enterprise-grade security and privacy compliance, including SOC2 Type II, HIPAA, and GDPR, ensures that your data is always protected.",
  "producthunt_url": "https://www.producthunt.com/products/maxim-ai",
  "crawl_timestamp": "2025-04-04T23:32:46.202594"
}