{
  "title": "OneSearch",
  "product_url": "https://chromewebstore.google.com/detail/onesearchbookmark-multi-a/jmeceipkifhfndacgnmcbhohnmgcbadn",
  "description": "Instantly search your bookmarks, explore multiple AI engines with one key, and organize your most-used sites. Easily access recently added and frequently visited bookmarks. Enjoy a sleek UI with night mode support for a seamless browsing experience.",
  "producthunt_url": "https://www.producthunt.com/products/onesearch-3",
  "crawl_timestamp": "2025-04-04T23:33:24.520226"
}