{
  "title": "SideTreeTab: Intuitive Tab Management",
  "product_url": "https://side-tree-tab.tuzi.ai/",
  "description": "Revolutionize your browsing experience with SideTreeTab \u2013 a powerful Chrome extension that brings intelligent tab organization directly into your browser's side panel. Inspired by the innovative design of Arc browser, SideTreeTab transforms how you navigate and manage your web browsing.\n\ud83c\udf3f Intelligent Tab Hierarchy\n\nAutomatically track your browsing journey\nCreate natural parent-child relationships between tabs\nVisualize how you navigate from page to page",
  "producthunt_url": "https://www.producthunt.com/products/sidetreetab-intuitive-tab-management",
  "crawl_timestamp": "2025-04-05T02:42:31.897691"
}