{
  "title": "Worlde AI",
  "product_url": "https://chromewebstore.google.com/detail/wordle-ai-from-appdron/hmephjaokbfmadofapdpfadcdheplmnm",
  "description": "Struggling with Wordle? Let AI transform your experience! Our Wordle Solver analyzes green, yellow, and gray tiles to offer tailored hints for smarter wins and faster solutions. Turn every frustrating guess into a confident victory. Play smarter!",
  "producthunt_url": "https://www.producthunt.com/products/worlde-ai",
  "crawl_timestamp": "2025-04-05T01:45:03.567127"
}