{
  "title": "YouTube PlayList Search",
  "product_url": "https://chromewebstore.google.com/detail/youtube-playlist-search/gbfangdjglbhhfkoglmdbnfcjajhpcfp",
  "description": "Frustrated because you can't find the YouTube playlist you want to save to? YouTube Playlist Search is a free Chrome extension. It adds the ability to search & filter your list of YouTube playlists.",
  "producthunt_url": "https://www.producthunt.com/products/youtube-playlist-search",
  "crawl_timestamp": "2025-04-05T04:01:06.810843"
}