{
  "title": "50+ Colorful Instagram Login Pages",
  "product_url": "https://tailwindgenie.com/tailwind-css-instagram-login",
  "description": "We\u2019ve got over 100 wacky Instagram login page designs made with Tailwind CSS. Each one is like a new outfit for your login\u2014some are super simple, and others are as colorful as a rainbow! Let\u2019s make logging in so fun that even your dog would want to do it!",
  "producthunt_url": "https://www.producthunt.com/products/50-colorful-instagram-login-pages",
  "crawl_timestamp": "2025-04-04T17:27:59.523752"
}