{
  "title": "Cocoon.ai",
  "product_url": "https://cocoon-demo-851564657364.us-east1.run.app/",
  "description": "Welcome to Cocoon.ai! Did you know that product trials using users' own data are 2\u20135\u00d7 more likely to convert? Our AI transforms your users' files into your data model in minutes, enabling personalized trials and onboarding. Try our CRM-based demo today!",
  "producthunt_url": "https://www.producthunt.com/products/cocoon-ai",
  "crawl_timestamp": "2025-04-04T18:13:02.716878"
}