{
  "title": "Free Dashboards by Master Metrics",
  "product_url": "https://mastermetrics.com/en/dashboard-de-marketing-gratuito/",
  "description": "Free Dashboards is a 100% free marketing visualization tool. Use marketing templates and create real-time reports in seconds without paying for connectors to include data from Google, Meta, Linkedin or TikTok. Besides, you can send data to Google Sheets.",
  "producthunt_url": "https://www.producthunt.com/products/free-dashboards-by-master-metrics",
  "crawl_timestamp": "2025-04-04T18:01:58.495989"
}