{
  "title": "Glosso - Scan Vocabulary",
  "product_url": "https://play.google.com/store/apps/details",
  "description": "\"Glosso transforms how you learn vocabulary! Simply scan words with the photo-scan feature. Whether on the go or reading, save and practice new words in your personalized list. Perfect for language learners, travelers, and language enthusiasts!",
  "producthunt_url": "https://www.producthunt.com/products/glosso-scan-vocabulary",
  "crawl_timestamp": "2025-04-04T19:16:47.316473"
}