{
  "title": "Instagram Growth Mastery Guide",
  "product_url": "https://goodsdude.gumroad.com/l/IGgrowth",
  "description": "Unlock Instagram growth mastery! \ud83d\udcc8 Get the ultimate guide to boost followers, make money, and hit millions of views. Learn positioning, viral content secrets, hashtag hacks, perfect posting times, and monetization strategies\u2014plus an exclusive bonus! \ud83d\ude80",
  "producthunt_url": "https://www.producthunt.com/products/instagram-growth-mastery-guide",
  "crawl_timestamp": "2025-04-04T22:02:34.409295"
}