{
  "title": "Manga Translate",
  "product_url": "https://apps.apple.com/us/app/manga-translate/id6502868308",
  "description": "Manga Translate uses advanced AI to deliver fast, accurate manga translations. Simply scan and translate manga into multiple languages while keeping the original art and story intact. Perfect for manga lovers seeking quick and seamless translations.",
  "producthunt_url": "https://www.producthunt.com/products/manga-translate",
  "crawl_timestamp": "2025-04-04T18:35:41.891363"
}