{
  "title": "RoleGuides Game Master Assistant Tool",
  "product_url": "https://roleguides.com/",
  "description": "Level-up your TTRPG experience with RoleGuides, the AI-powered GM assistant. Generate NPC dialogue, random encounters, and dynamic story elements to streamline your campaigns. Perfect for Game Masters who want to focus on storytelling and gameplay without prep",
  "producthunt_url": "https://www.producthunt.com/products/roleguides-game-master-assistant-tool",
  "crawl_timestamp": "2025-04-04T17:37:11.335978"
}