{
  "title": "SaaSphere NextJS SaaS Boilerplate",
  "product_url": "https://saasphere.dev/",
  "description": "SaaSphere NextJS SaaS boilerplate is a customizable template for building SaaS apps. Built with NextJS, Drizzle, Tailwind, and ShadCN UI. Features include a CMS-able blog, authentication, billing (one-time/subscription), notifications, admin panel, and more.",
  "producthunt_url": "https://www.producthunt.com/products/saasphere-nextjs-saas-boilerplate",
  "crawl_timestamp": "2025-04-04T20:13:10.794725"
}