{
  "title": "Sales Tools AI",
  "product_url": "https://salestoolsai.top/",
  "description": "\ud83e\udde0 AI is changing Sales processes. Let's unlock your full potential with the best products dedicated to Sales people \u2728 With more than 1300 products, it's now fast & easy to create a powerful sales stack \u2705 Start rising to the top, for free: salestoolsai.top",
  "producthunt_url": "https://www.producthunt.com/products/sales-tools-ai",
  "crawl_timestamp": "2025-04-04T19:33:33.628768"
}