{
  "title": "SIP AI : Food & Drink AI",
  "product_url": "https://play.google.com/store/apps/details",
  "description": "Sip AI provides personalized food and drink recipes to suit your lifestyle. Discover healthy meals, smoothies, immunity boosters, and stress-relief drinks. Enjoy easy step-by-step instructions and expert guidance for wellness-focused, delicious choices daily.",
  "producthunt_url": "https://www.producthunt.com/products/sip-ai-food-drink-ai",
  "crawl_timestamp": "2025-04-04T17:22:30.590536"
}