{
  "title": "Viewpoints",
  "product_url": "https://apps.apple.com/us/app/viewpoints/id1077165555",
  "description": "ViewPoints is a mobile app that lets you see whats happening around your community. It lets you know how many people are there and what they're saying in real time. Local bars, sports events, malls, gyms, parks etc and notifies you when your friends are there.",
  "producthunt_url": "https://www.producthunt.com/products/viewpoints",
  "crawl_timestamp": "2025-04-04T18:18:55.890996"
}