{
  "title": "Virtual Coaching Ally by ALFAMIND",
  "product_url": "https://alfamind.io/",
  "description": "Think of Ally as your pocket coach. Just share your personal context, and Ally does the rest: finding coaches that match your style, recommending courses, tracking progress, guiding reflections, and suggesting next steps\u2014no endless forms or random matches.",
  "producthunt_url": "https://www.producthunt.com/products/virtual-coaching-ally-by-alfamind",
  "crawl_timestamp": "2025-04-04T22:21:05.795078"
}