{
  "title": "Voice AI Telegram Bot",
  "product_url": "https://t.me/voiceeaibot",
  "description": "Instant Voice-to-Text Converter Convert voice messages into text instantly in any language! Our bot transcribes your audio messages quickly and accurately, making it easier to read and share Just send a voice message, and get the text version instantly!\ud83c\udf99\ufe0f\u27a1\ufe0f\ud83d\udcdd",
  "producthunt_url": "https://www.producthunt.com/products/voice-ai-telegram-bot",
  "crawl_timestamp": "2025-04-07T09:37:43.487232"
}