{
  "title": "Amiry \u2013 AI-Powered Smart City Routes",
  "product_url": "https://amiry.io/",
  "description": "Amiry is an AI-powered city guide that builds personalized routes in seconds. Just enter your time, interests, and transport mode\u2014walk, bike, or run\u2014and explore effortlessly. No planning, no research, just the best spots with real-time voice guidance.",
  "producthunt_url": "https://www.producthunt.com/products/amiry-ai-powered-smart-city-routes",
  "crawl_timestamp": "2025-04-06T11:26:10.528146"
}