{
  "title": "Foody - Calorie Tracker",
  "product_url": "https://apps.apple.com/ro/app/foody-calorie-tracker/id6743651732",
  "description": "The easy-to-use calorie and macro tracker designed to help you reach your fitness goals. Whether you\u2019re aiming to lose weight, gain muscle, or simply maintain a healthy diet, Foody makes tracking your food and progress",
  "producthunt_url": "https://www.producthunt.com/products/foody-calorie-tracker",
  "crawl_timestamp": "2025-04-06T13:42:02.282962"
}