{
  "title": "MenuCopy - View copied text & image",
  "product_url": "https://apps.apple.com/app/menucopy-clipboard-saver/id6742753291",
  "description": "MenuCopy is a clipboard manager for macOS that allows you to simultaneously view and instantly copy your most recently saved text and image from the menu bar. Designed for productivity, it keeps your clipboard history private, organized, and quickly accessible",
  "producthunt_url": "https://www.producthunt.com/products/menucopy-view-copied-text-image",
  "crawl_timestamp": "2025-04-06T14:05:33.175838"
}