{
  "title": "Baby Alarm Clock",
  "product_url": "https://apps.apple.com/pl/app/alarm-clock-for-baby-kids/id6475605888",
  "description": "Baby Alarm Clock \u2013 Train Your Baby for Consistent Sleep Turn any device into \"red light\" - \"green light\" lamp and get your mornings back. This method teaches babies and toddlers to associate colors with sleep cycles, creating a calming and structured routine.",
  "producthunt_url": "https://www.producthunt.com/products/baby-alarm-clock",
  "crawl_timestamp": "2025-04-05T20:19:53.876713"
}