{
  "title": "Billy - Comparte los gastos de un ticket",
  "product_url": "https://splitbilly.com/",
  "description": "\u00bfPara qu\u00e9 sirve Billy? Simplifica el reparto de un ticket: escanea y comparte para que cada uno seleccione sus consumiciones. - Usa Billy directamente desde tu navegador - Un simple link conecta a todos los participantes - Gratis, si registros.",
  "producthunt_url": "https://www.producthunt.com/products/billy-comparte-los-gastos-de-un-ticket",
  "crawl_timestamp": "2025-04-05T20:25:55.706191"
}