{
  "title": "Bitdefender Security for Creators",
  "product_url": "https://www.bitdefender.com/en-us/consumer/security-for-creators",
  "description": "Bitdefender Security for Creators is designed specifically to address the unique challenges faced by content creators - Proactive Protection - Phishing Detection - Hacking Prevention - Channel Monitoring - Recovery Assistance",
  "producthunt_url": "https://www.producthunt.com/products/bitdefender-security-for-creators",
  "crawl_timestamp": "2025-04-05T20:08:59.439420"
}