{
  "title": "CodeSwissKnife Developer Tools for iPad",
  "product_url": "https://apps.apple.com/us/app/codeswissknife-developer-tools/id6742375516",
  "description": "CodeSwissKnife for iPad is a powerful, all-in-one developer utility designed to simplify and accelerate your daily tasks. Over 17 meticulously crafted developer tools designed to handle your everyday tasks with ease. The Ultimate Developer Toolkit.",
  "producthunt_url": "https://www.producthunt.com/products/codeswissknife-developer-tools-for-ipad",
  "crawl_timestamp": "2025-04-06T00:58:21.617268"
}