{
  "title": "Go Steps AI: Step Counter",
  "product_url": "https://apps.apple.com/in/app/go-steps-ai-step-counter/id6739782103",
  "description": "Go Steps - a simple step-counting app to help you move, stay active, and build lasting habits. No gimmicks, no distractions\u2014just a way to take control of your health, one step at a time. Because real progress isn\u2019t instant\u2014it\u2019s earned.",
  "producthunt_url": "https://www.producthunt.com/products/go-steps-ai-step-counter",
  "crawl_timestamp": "2025-04-05T22:08:44.660024"
}