{
  "title": "Hide",
  "product_url": "https://hide.sh/",
  "description": "Hide is an AI coding agent built for ambitious teams in fast-growing companies, helping you code faster and ship more. It translates your requirements into code while working directly in your local repositories, automating development end-to-end. With built-in shell access and an integrated code editor, it modifies files, installs dependencies, runs tests, and follows your team\u2019s architecture, coding standards, and best practices.",
  "producthunt_url": "https://www.producthunt.com/products/hide",
  "crawl_timestamp": "2025-04-06T00:05:44.098383"
}