{
  "title": "IGFollow AI - Auto Follow",
  "product_url": "https://chromewebstore.google.com/detail/igfollow-ai-otomatik-taki/gjledilecenicgdidfemjoeecgagokpe",
  "description": "IGFollow AI helps you grow your Instagram account effortlessly with advanced artificial intelligence. Reach your target audience faster and expand your profile safely with smart automation.",
  "producthunt_url": "https://www.producthunt.com/products/igfollow-ai-auto-follow",
  "crawl_timestamp": "2025-04-05T22:07:27.902680"
}