{
  "title": "Instagram Unfollow AI Manage Unfollowers",
  "product_url": "https://chromewebstore.google.com/detail/instagram-unfollow-ai-tak/lbanojlcfgehondfpeipfpmdfipbjlhh",
  "description": "Easily manage your followers and boost engagement with Instagram Unfollow AI \u2013 a free and powerful tool that helps you identify and unfollow users who don\u2019t follow you back. Keep your profile clean, efficient, and focused on genuine connections.",
  "producthunt_url": "https://www.producthunt.com/products/instagram-unfollow-ai-manage-unfollowers",
  "crawl_timestamp": "2025-04-05T22:07:26.101450"
}