{
  "title": "Kirigami Creations: 3D Paper Craft Kit",
  "product_url": "https://34market.online/products/enchanted-kirigami-creations-3d-paper-craft-kit-for-adults-kids-diy-family-bonding-stress-relief-creative-fun",
  "description": "\u2728&nbsp;Unlock the Magic of Paper Art with Enchanted Kirigami Creations!&nbsp;\u2728 Transform ordinary paper into breathtaking 3D masterpieces with our all-in-one&nbsp;Kirigami Craft Kit\u2014designed for adults&nbsp;and&nbsp;kids to create, bond, and unwind together!",
  "producthunt_url": "https://www.producthunt.com/products/kirigami-creations-3d-paper-craft-kit",
  "crawl_timestamp": "2025-04-06T01:02:18.283892"
}