{
  "title": "WatchList: The Movie App",
  "product_url": "https://apps.apple.com/us/app/watchlist-the-movie-app/id6739383528",
  "description": "WatchList: The Movie App is your personal movie assistant, designed to make movie nights stress-free and exciting. Whether you're looking for a film for date night, a hidden gem for downtime, or a group-friendly pick for friends, WatchList has you covered.",
  "producthunt_url": "https://www.producthunt.com/products/watchlist-the-movie-app",
  "crawl_timestamp": "2025-04-05T21:07:53.426180"
}