{
  "title": "WikiTok IOS",
  "product_url": "https://apps.apple.com/us/app/wikitok-scroll-articles/id6741830503",
  "description": "Discover fascinating Wiki articles with a simple swipe! WikiTok brings you an endless stream of knowledge in a familiar, engaging format. Replace your doomscrolling with encyclopedic rabbit holes. Perfect for learning something new every day.",
  "producthunt_url": "https://www.producthunt.com/products/wikitok-ios",
  "crawl_timestamp": "2025-04-05T22:45:20.727786"
}