{
  "title": "Atlas - Tasks + Calendar",
  "product_url": "https://apps.apple.com/us/app/atlas-tasks-calendar/id1494058729",
  "description": "Atlas is your all-in-one task manager. Organize tasks by lists, set reminders, track deadlines, and prioritize with ease. Use tags, subtasks, and natural language input to stay on top of your goals. Available on macOS, iOS, and iPadOS.",
  "producthunt_url": "https://www.producthunt.com/products/atlas-tasks-calendar",
  "crawl_timestamp": "2025-04-05T13:24:59.361102"
}