{
  "title": "Githubhunt",
  "product_url": "https://githubhunt.top/",
  "description": "Githubhunt - AI-powered GitHub repository search engine that helps you find the most relevant repositories using natural language. \u57fa\u4e8e\u4eba\u5de5\u667a\u80fd\u7684 GitHub \u4ed3\u5e93\u641c\u7d22\u5f15\u64ce\uff0c\u5e2e\u52a9\u4f60\u7528\u81ea\u7136\u8bed\u8a00\u627e\u5230\u6700\u76f8\u5173\u7684\u4ee3\u7801\u4ed3\u5e93\u3002",
  "producthunt_url": "https://www.producthunt.com/products/githubhunt-2",
  "crawl_timestamp": "2025-04-05T13:04:53.715822"
}