{
  "title": "LPagery Bulk Page Creator for WordPress",
  "product_url": "https://lpagery.io/",
  "description": "LPagery 2.0 makes bulk landing page creation easier than ever with a redesigned UI, new knowledge base, improved page creation tools, and more. Perfect for anyone needing lots of unique, SEO-friendly pages in minutes! Just from a source file and template page!",
  "producthunt_url": "https://www.producthunt.com/products/lpagery-bulk-page-creator-for-wordpress",
  "crawl_timestamp": "2025-04-05T14:12:15.823151"
}