{
  "title": "MedKid",
  "product_url": "https://medkid.app/",
  "description": "MedKid is a secure mobile application designed to help parents track, manage, and share their children\u2019s health information. It offers features such as instant data synchronization across family devices through the Family+ subscription, smart search capabilities using local AI text recognition, and end-to-end encryption to ensure data privacy. The app is available for both iOS and Android devices.",
  "producthunt_url": "https://www.producthunt.com/products/medkid",
  "crawl_timestamp": "2025-04-05T10:47:18.911374"
}