{
  "title": "SuperPower Generator",
  "product_url": "https://superpowergenerator.top/",
  "description": "Unleash your imagination with the SuperPower Generator \u26a1! Instantly generate unique and quirky superpowers, from elemental abilities, X-men Powers to anime tricks or even completely useless powers. Perfect for writers, role-players, or just for fun!",
  "producthunt_url": "https://www.producthunt.com/products/superpower-generator-2",
  "crawl_timestamp": "2025-04-05T11:14:17.604183"
}