{
  "title": "Vesuv",
  "product_url": "https://www.vesuv.fr/",
  "description": "Nous aidons les \u00e9quipes \u00e0 appliquer les proc\u00e9dures de l'entreprise pour \u00e9liminer les anomalies et assurer la tra\u00e7abilit\u00e9.\nChez Vesuv, nous sommes d\u00e9termin\u00e9s \u00e0 aider nos clients \u00e0 piloter le changement en pla\u00e7ant la digitalisation au service de l\u2019excellence op\u00e9rationnelle.\n\nNotre mission consiste \u00e0 aider les dirigeants et managers \u00e0 am\u00e9liorer leur mani\u00e8re d'assurer la politique qualit\u00e9 gr\u00e2ce \u00e0 un syst\u00e8me de management digital, simple et rapide \u00e0 mettre en place.",
  "producthunt_url": "https://www.producthunt.com/products/vesuv",
  "crawl_timestamp": "2025-04-05T10:17:12.933838"
}